setup.cfg
setup.py
rgbxy/__init__.py
rgbxy.egg-info/PKG-INFO
rgbxy.egg-info/SOURCES.txt
rgbxy.egg-info/dependency_links.txt
rgbxy.egg-info/top_level.txt