Metadata-Version: 1.0
Name: rgbxy
Version: 0.5
Summary: RGB conversion tool written in Python for Philips Hue.
Home-page: https://github.com/benknight/hue-python-rgb-converter
Author: Ben Knight
Author-email: ben@benknight.me
License: MIT
Keywords: philips hue light rgb xy
Platform: UNKNOWN
